{
  "name": "Science Bowl",
  "imgsrc": "sciencebowl.jpg",
  "description": "Participate in a competitive math and science competition involving a variety of subjects including the latest information from the U.S. National Labs. Sponsored by the DOE. This is another club that allows students to explore science besides SciOly.",
  "officers": [
    {
      "position": "President",
      "name": "jmaloney@cps.edu"
    
    },
    {
      "position": "Advisor",
      "name": "Daniel Kang"
    }
  ],
  "announcements": [
    {
      "title": "Meetings",
      "description": "Club meetings take place Wednesday after school in room 310."
    }
  ],
  "links": [
    {
      "title": "Team Page",
      "link": ""
    }
  ]
}
