{
  "name": "Social Club",
  "imgsrc": "socialclub.jpg",
  "description": "The WY Social Club organizes social events and networking among students to fundraise for charitable organizations.",
  "officers": [
    {
      "position": "President",
      "name": "jmedina136@cps.edu"
    
    },
    {
      "position": "Advisor",
      "name": "Mr. Billy Poole Harris"
    }
  ],
  "announcements": [
    {
      "title": "Meetings",
      "description": "Club meetings take place Wednesday after school in room TBD."
    }
  ],
  "links": [
    {
      "title": "Team Page",
      "link": ""
    }
  ]
}
